{
	"name": "trg_copy_dl_to_sql",
	"properties": {
		"description": "Copy all from datalake to SQL stg tables",
		"annotations": [],
		"runtimeState": "Started",
		"pipelines": [
			{
				"pipelineReference": {
					"referenceName": "pip_copy_all_dl_sql",
					"type": "PipelineReference"
				}
			}
		],
		"type": "ScheduleTrigger",
		"typeProperties": {
			"recurrence": {
				"frequency": "Day",
				"interval": 1,
				"startTime": "2022-05-10T18:49:00",
				"timeZone": "Central Europe Standard Time",
				"schedule": {
					"minutes": [
						0
					],
					"hours": [
						7
					]
				}
			}
		}
	}
}